pack/__init__.py
pack/pack.py
TestPackageerty-0.0.2.dist-info/METADATA
TestPackageerty-0.0.2.dist-info/WHEEL
TestPackageerty-0.0.2.dist-info/top_level.txt
TestPackageerty-0.0.2.dist-info/RECORD
