Metadata-Version: 2.1
Name: TestPackageerty
Version: 0.0.2
Summary: Lib
Author: Test
Author-email: aae5654ae@mozmail.com
License: MIT
Classifier: Programming Language :: Python :: 3
Classifier: License :: OSI Approved :: MIT License
Classifier: Operating System :: OS Independent
